MANIFEST.in
README.md
setup.py
setuptools_i18n.py
setuptools_i18n.egg-info/PKG-INFO
setuptools_i18n.egg-info/SOURCES.txt
setuptools_i18n.egg-info/dependency_links.txt
setuptools_i18n.egg-info/entry_points.txt
setuptools_i18n.egg-info/top_level.txt